udtube/__init__.py
udtube/callbacks.py
udtube/cli.py
udtube/defaults.py
udtube/encoders.py
udtube/models.py
udtube/modules.py
udtube/schedulers.py
udtube/special.py
udtube/data/__init__.py
udtube/data/batches.py
udtube/data/collators.py
udtube/data/conllu.py
udtube/data/datamodules.py
udtube/data/datasets.py
udtube/data/edit_scripts.py
udtube/data/indexes.py
udtube/data/logits.py
udtube/data/mappers.py
udtube-0.1.8.dist-info/licenses/LICENSE.txt
udtube-0.1.8.dist-info/METADATA
udtube-0.1.8.dist-info/WHEEL
udtube-0.1.8.dist-info/entry_points.txt
udtube-0.1.8.dist-info/top_level.txt
udtube-0.1.8.dist-info/RECORD
